low_level_python/__init__.py
low_level_python/c_files/clibrary.c
low_level_python/llp_compiler.py
low_level_python/llp_types.py
low_level_python/llp_wrapper.py
low_level_python-0.1.1.dist-info/METADATA
low_level_python-0.1.1.dist-info/WHEEL
low_level_python-0.1.1.dist-info/RECORD
